ldkjsms/__init__.py
ldkjsms/examples.py
ldkjsms/sms_client.py
ldkjclient-0.1.2.dist-info/METADATA
ldkjclient-0.1.2.dist-info/WHEEL
ldkjclient-0.1.2.dist-info/top_level.txt
ldkjclient-0.1.2.dist-info/RECORD
