Metadata-Version: 2.1
Name: ldkjclient
Version: 0.1.2
Summary: 凌渡科技客户端
Home-page: https://www.lingduyun.net/
Author: xuxiadong
Author-email: xuxiaodong@lingduyun.net
Requires-Dist: requests >=2.0.0
